packagestarter/__init__.py
packagestarter/base_templates.py
packagestarter/git_initializer.py
packagestarter/packagestarter.py
packagestarter/structure_creation.py
packagestarter/templates/docs/BUILD.md.jinja
packagestarter/templates/docs/index.md.jinja
packagestarter/templates/root/.gitignore.jinja
packagestarter/templates/root/LICENSE.jinja
packagestarter/templates/root/Makefile.jinja
packagestarter/templates/root/README.md.jinja
packagestarter/templates/root/pyproject.toml.jinja
packagestarter/templates/root/requirements.txt.jinja
packagestarter/templates/src/package_name/__init__.py.jinja
packagestarter/templates/tests/__init__.py.jinja
packagestarter/templates/tests/conftest.py.jinja
packagestarter/templates/tests/test_main.py.jinja
packagestarter-0.0.11.dist-info/LICENSE
packagestarter-0.0.11.dist-info/METADATA
packagestarter-0.0.11.dist-info/WHEEL
packagestarter-0.0.11.dist-info/entry_points.txt
packagestarter-0.0.11.dist-info/RECORD
